LinkedDicom/CLI_SCP.py
LinkedDicom/LinkedDicom.owl
LinkedDicom/LinkedDicom.py
LinkedDicom/OntologyService.py
LinkedDicom/RDFService.py
LinkedDicom/__init__.py
LinkedDicom/cli.py
LinkedDicom/rt/__init__.py
LinkedDicom/rt/dvh.py
LinkedDicom-0.3.0.dist-info/METADATA
LinkedDicom-0.3.0.dist-info/WHEEL
LinkedDicom-0.3.0.dist-info/entry_points.txt
LinkedDicom-0.3.0.dist-info/top_level.txt
LinkedDicom-0.3.0.dist-info/RECORD
