Metadata-Version: 2.1
Name: LinkedDicom
Version: 0.3.0
Summary: A package to extract DICOM header data and store this in RDF
Home-page: https://github.com/MaastrichtU-CDS/LinkedDicom
Author: Johan van Soest
Author-email: j.vansoest@maastrichtuniversity.nl
License: Apache 2.0
Requires-Dist: pydicom
Requires-Dist: rdflib
Requires-Dist: requests
Requires-Dist: click
Requires-Dist: pynetdicom
Requires-Dist: dicompyler-core
